{
  "project_info": {
    "project_number": "1060294207824",
    "project_id": "kashipara-2657d",
    "storage_bucket": "kashipara-2657d.appspot.com"
  },
  "client": [
    {
      "client_info": {
        "mobilesdk_app_id": "1:1060294207824:android:2f032a97469c5ccc3f6455",
        "android_client_info": {
          "package_name": "com.example.Kashipara"
        }
      },
      "oauth_client": [
        {
          "client_id": "1060294207824-jp3m57rcsbenh15f1ej1mmf7rosiic3r.apps.googleusercontent.com",
          "client_type": 3
        }
      ],
      "api_key": [
        {
          "current_key": "AIzaSyA6Qra-nYNXrKinzR0YpMSG4orjObGjfKs"
        }
      ],
      "services": {
        "appinvite_service": {
          "other_platform_oauth_client": [
            {
              "client_id": "1060294207824-jp3m57rcsbenh15f1ej1mmf7rosiic3r.apps.googleusercontent.com",
              "client_type": 3
            }
          ]
        }
      }
    },
    {
      "client_info": {
        "mobilesdk_app_id": "1:1060294207824:android:f70abbd03f87e93d3f6455",
        "android_client_info": {
          "package_name": "com.example.kumarGroup"
        }
      },
      "oauth_client": [
        {
          "client_id": "1060294207824-jp3m57rcsbenh15f1ej1mmf7rosiic3r.apps.googleusercontent.com",
          "client_type": 3
        }
      ],
      "api_key": [
        {
          "current_key": "AIzaSyA6Qra-nYNXrKinzR0YpMSG4orjObGjfKs"
        }
      ],
      "services": {
        "appinvite_service": {
          "other_platform_oauth_client": [
            {
              "client_id": "1060294207824-jp3m57rcsbenh15f1ej1mmf7rosiic3r.apps.googleusercontent.com",
              "client_type": 3
            }
          ]
        }
      }
    }
  ],
  "configuration_version": "1"
}